LICENSE.txt
README.md
pyproject.toml
setup.py
sequence/__init__.py
sequence/__version__.py
sequence/cli/__init__.py
sequence/cli/cli.py
sequence/cli/parser.py
sequence/cli/commands/__init__.py
sequence/cli/commands/list.py
sequence/cli/commands/sequence.py
sequence/core/__init__.py
sequence/core/core.py
sequence/core/finite_type.py
sequence/core/infinite_type.py
sequence/core/mixin.py
sequence/core/utils/__init__.py
sequence/core/utils/exceptions.py
sequence/core/utils/functions.py
sequence/core/utils/validation.py
sequence/sequences/__init__.py
sequence/sequences/integer/__init__.py
sequence/sequences/integer/explicit.py
sequence/sequences/integer/explicit_generalised.py
sequence/sequences/integer/finite.py
sequence/sequences/integer/periodic.py
sequence/sequences/integer/periodic_generalised.py
sequence/sequences/integer/property_defined.py
sequence/sequences/integer/property_defined_generalised.py
sequence/sequences/integer/recursive.py
sequence/sequences/integer/recursive_generalised.py
sequentium.egg-info/PKG-INFO
sequentium.egg-info/SOURCES.txt
sequentium.egg-info/dependency_links.txt
sequentium.egg-info/entry_points.txt
sequentium.egg-info/top_level.txt