Metadata-Version: 2.1
Name: sequentium
Version: 0.0.4
Summary: Sequentium is a user-friendly package that implements various well-known sequences, providing a seamless and intuitive experience for the user
Home-page: https://github.com/VascoSch92/sequentium
Author: Vasco Schiavo
Author-email: vasco.schiavo@protonmail.com
License: MIT
Keywords: math,mathematics,sequence,fibonacci
Platform: UNKNOWN
Classifier: Development Status :: 5 - Production/Stable
Classifier: Intended Audience :: Education
Classifier: Intended Audience :: End Users/Desktop
Classifier: Intended Audience :: Science/Research
Classifier: License :: OSI Approved :: MIT License
Classifier: Programming Language :: Python :: 3.9
Classifier: Programming Language :: Python :: 3.10
Classifier: Programming Language :: Python :: 3.11
Classifier: Programming Language :: Python :: 3.12
Classifier: Topic :: Education
Classifier: Topic :: Scientific/Engineering :: Mathematics
Requires-Python: >=3.9
License-File: LICENSE.txt
